Arjun_STT/__init__.py
Arjun_STT/main.py
Arjun_STT/web/index.html
Arjun_STT/web/script.js
Arjun_STT/web/styles.css
arjun_stt-0.1.2.dist-info/METADATA
arjun_stt-0.1.2.dist-info/WHEEL
arjun_stt-0.1.2.dist-info/top_level.txt
arjun_stt-0.1.2.dist-info/RECORD
